CHANGELOG.txt
LICENCE.txt
MANIFEST.in
README.txt
__init__.py
setup.py
sripluscalculator.egg-info/PKG-INFO
sripluscalculator.egg-info/SOURCES.txt
sripluscalculator.egg-info/dependency_links.txt
sripluscalculator.egg-info/top_level.txt
venv/Lib/site-packages/_virtualenv.py
venv/Lib/site-packages/six.py
venv/Lib/site-packages/zipp.py
venv/Lib/site-packages/Pygments-2.10.0.dist-info/entry_points.txt
venv/Lib/site-packages/Pygments-2.10.0.dist-info/top_level.txt
venv/Lib/site-packages/_distutils_hack/__init__.py
venv/Lib/site-packages/_distutils_hack/override.py
venv/Lib/site-packages/bleach/__init__.py
venv/Lib/site-packages/bleach/callbacks.py
venv/Lib/site-packages/bleach/html5lib_shim.py
venv/Lib/site-packages/bleach/linkifier.py
venv/Lib/site-packages/bleach/sanitizer.py
venv/Lib/site-packages/bleach/utils.py
venv/Lib/site-packages/bleach-4.1.0.dist-info/top_level.txt
venv/Lib/site-packages/bleach/_vendor/__init__.py
venv/Lib/site-packages/bleach/_vendor/parse.py
venv/Lib/site-packages/bleach/_vendor/vendor.txt
venv/Lib/site-packages/bleach/_vendor/html5lib/__init__.py
venv/Lib/site-packages/bleach/_vendor/html5lib/_ihatexml.py
venv/Lib/site-packages/bleach/_vendor/html5lib/_inputstream.py
venv/Lib/site-packages/bleach/_vendor/html5lib/_tokenizer.py
venv/Lib/site-packages/bleach/_vendor/html5lib/_utils.py
venv/Lib/site-packages/bleach/_vendor/html5lib/constants.py
venv/Lib/site-packages/bleach/_vendor/html5lib/html5parser.py
venv/Lib/site-packages/bleach/_vendor/html5lib/serializer.py
venv/Lib/site-packages/bleach/_vendor/html5lib-1.1.dist-info/top_level.txt
venv/Lib/site-packages/bleach/_vendor/html5lib/_trie/__init__.py
venv/Lib/site-packages/bleach/_vendor/html5lib/_trie/_base.py
venv/Lib/site-packages/bleach/_vendor/html5lib/_trie/py.py
venv/Lib/site-packages/bleach/_vendor/html5lib/filters/__init__.py
venv/Lib/site-packages/bleach/_vendor/html5lib/filters/alphabeticalattributes.py
venv/Lib/site-packages/bleach/_vendor/html5lib/filters/base.py
venv/Lib/site-packages/bleach/_vendor/html5lib/filters/inject_meta_charset.py
venv/Lib/site-packages/bleach/_vendor/html5lib/filters/lint.py
venv/Lib/site-packages/bleach/_vendor/html5lib/filters/optionaltags.py
venv/Lib/site-packages/bleach/_vendor/html5lib/filters/sanitizer.py
venv/Lib/site-packages/bleach/_vendor/html5lib/filters/whitespace.py
venv/Lib/site-packages/bleach/_vendor/html5lib/treeadapters/__init__.py
venv/Lib/site-packages/certifi-2021.10.8.dist-info/top_level.txt
venv/Lib/site-packages/charset_normalizer-2.0.9.dist-info/entry_points.txt
venv/Lib/site-packages/charset_normalizer-2.0.9.dist-info/top_level.txt
venv/Lib/site-packages/colorama-0.4.4.dist-info/LICENSE.txt
venv/Lib/site-packages/colorama-0.4.4.dist-info/top_level.txt
venv/Lib/site-packages/docutils-0.18.1.dist-info/COPYING.txt
venv/Lib/site-packages/docutils-0.18.1.dist-info/top_level.txt
venv/Lib/site-packages/idna-3.3.dist-info/top_level.txt
venv/Lib/site-packages/importlib_metadata-4.10.0.dist-info/top_level.txt
venv/Lib/site-packages/keyring-23.4.0.dist-info/entry_points.txt
venv/Lib/site-packages/keyring-23.4.0.dist-info/top_level.txt
venv/Lib/site-packages/packaging-21.3.dist-info/top_level.txt
venv/Lib/site-packages/pip-21.1.2.dist-info/LICENSE.txt
venv/Lib/site-packages/pip-21.1.2.dist-info/entry_points.txt
venv/Lib/site-packages/pip-21.1.2.dist-info/top_level.txt
venv/Lib/site-packages/pkginfo-1.8.2.dist-info/LICENSE.txt
venv/Lib/site-packages/pkginfo-1.8.2.dist-info/entry_points.txt
venv/Lib/site-packages/pkginfo-1.8.2.dist-info/top_level.txt
venv/Lib/site-packages/pyparsing-3.0.6.dist-info/top_level.txt
venv/Lib/site-packages/pywin32_ctypes-0.2.0.dist-info/LICENSE.txt
venv/Lib/site-packages/pywin32_ctypes-0.2.0.dist-info/top_level.txt
venv/Lib/site-packages/readme_renderer-32.0.dist-info/entry_points.txt
venv/Lib/site-packages/readme_renderer-32.0.dist-info/top_level.txt
venv/Lib/site-packages/requests-2.26.0.dist-info/top_level.txt
venv/Lib/site-packages/requests_toolbelt-0.9.1.dist-info/top_level.txt
venv/Lib/site-packages/rfc3986-1.5.0.dist-info/top_level.txt
venv/Lib/site-packages/setuptools-57.0.0.dist-info/dependency_links.txt
venv/Lib/site-packages/setuptools-57.0.0.dist-info/entry_points.txt
venv/Lib/site-packages/setuptools-57.0.0.dist-info/top_level.txt
venv/Lib/site-packages/six-1.16.0.dist-info/top_level.txt
venv/Lib/site-packages/tqdm-4.62.3.dist-info/entry_points.txt
venv/Lib/site-packages/tqdm-4.62.3.dist-info/top_level.txt
venv/Lib/site-packages/twine-3.7.1.dist-info/entry_points.txt
venv/Lib/site-packages/twine-3.7.1.dist-info/top_level.txt
venv/Lib/site-packages/urllib3-1.26.7.dist-info/LICENSE.txt
venv/Lib/site-packages/urllib3-1.26.7.dist-info/top_level.txt
venv/Lib/site-packages/webencodings-0.5.1.dist-info/top_level.txt
venv/Lib/site-packages/wheel-0.36.2.dist-info/LICENSE.txt
venv/Lib/site-packages/wheel-0.36.2.dist-info/entry_points.txt
venv/Lib/site-packages/wheel-0.36.2.dist-info/top_level.txt
venv/Lib/site-packages/zipp-3.6.0.dist-info/top_level.txt
